{
    "id": 308,
    "packet_id": 20,
    "packet_name": "MCP_CREATEQUEUE",
    "packet_direction_id": 2,
    "packet_application_layer_id": 3,
    "packet_transport_layer_id": 1,
    "options_bitmask": 3,
    "brief_html": "<p>Position in line to create a game.</p>",
    "used_by": [
        1144144982,
        1144150096
    ],
    "author_username": "BNETDocs",
    "uri": "/packet/308/mcp-createqueue",
    "created_datetime": "2010-07-15T02:47:39+00:00",
    "edited_datetime": null,
    "format": "(UINT32) Position",
    "remarks_html": "<p>Position in line to create a game.</p>",
    "comments": []
}
