{
    "id": 334,
    "packet_id": 52,
    "packet_name": "SID_QUERYREALMS",
    "packet_direction_id": 1,
    "packet_application_layer_id": 1,
    "packet_transport_layer_id": 1,
    "options_bitmask": 7,
    "brief_html": "<p>Requests a realm listing.</p>",
    "used_by": [
        1144144982,
        1144150096
    ],
    "author_username": "unknown",
    "uri": "/packet/334/sid-queryrealms",
    "created_datetime": "2010-07-15T02:47:39+00:00",
    "edited_datetime": null,
    "format": "(UINT32) Unused (0)\r\n(UINT32) Unused (0)\r\n(STRING) Unknown (empty)",
    "remarks_html": "<p>Requests a realm listing.</p>\n<p>This packet is no longer used. SID_QUERYREALMS2 is used instead.</p>",
    "comments": []
}
